gevent_websocket-0.10.dist-info/DESCRIPTION.rst
gevent_websocket-0.10.dist-info/METADATA
gevent_websocket-0.10.dist-info/RECORD
gevent_websocket-0.10.dist-info/WHEEL
gevent_websocket-0.10.dist-info/metadata.json
gevent_websocket-0.10.dist-info/top_level.txt
geventwebsocket/__init__.py
geventwebsocket/_compat.py
geventwebsocket/exceptions.py
geventwebsocket/handler.py
geventwebsocket/logging.py
geventwebsocket/resource.py
geventwebsocket/server.py
geventwebsocket/utf8validator.py
geventwebsocket/utils.py
geventwebsocket/websocket.py
geventwebsocket/gunicorn/__init__.py
geventwebsocket/gunicorn/workers.py
geventwebsocket/protocols/__init__.py
geventwebsocket/protocols/base.py
geventwebsocket/protocols/wamp.py
