Metadata-Version: 2.0
Name: gevent-websocket
Version: 0.10
Summary: Websocket handler for the gevent pywsgi server, a Python network library
Home-page: https://www.gitlab.com/noppo/gevent-websocket
Author: Jeffrey Gelens
Author-email: jeffrey@noppo.pro
License: Copyright 2011-2013 Jeffrey Gelens <jeffrey@noppo.pro>
Requires-Dist: gevent
